dataflow/__init__.py
dataflow/config.py
dataflow/hub_api.py
dataflow/logger.py
dataflow/sampler.py
dataflow/utils.py
dataflow/cli/__init__.py
dataflow/cli/auth.py
dataflow/cloud/__init__.py
dataflow/cloud/cluster.py
dataflow/cloud/container.py
dataflow/cloud/iam_blocked_check.py
dataflow/cloud/logger.py
dataflow/collections/__init__.py
dataflow/collections/_store_version.py
dataflow/collections/client_manager.py
dataflow/collections/dataset/__init__.py
dataflow/collections/dataset/core.py
dataflow/collections/dataset/logger.py
dataflow/collections/tensor/__init__.py
dataflow/collections/tensor/core.py
dataflow/creds/__init__.py
dataflow/creds/aws.py
dataflow/creds/creds.py
dataflow/creds/logger.py
dataflow/dataset_generators/__init__.py
dataflow/dataset_generators/sampler/__init__.py
dataflow/dataset_generators/sampler/sampler.py
dataflow/dataset_generators/tests/__init__.py
dataflow/dataset_generators/tests/test_flow.py
dataflow/dataset_generators/tests/intelinair/__init__.py
dataflow/dataset_generators/tests/intelinair/test_ingestor.py
dataflow/dataset_generators/tests/intelinair/test_sampler.py
dataflow/ingestor/intelinair/logger.py
hub_dataflow-0.9.4.dist-info/METADATA
hub_dataflow-0.9.4.dist-info/WHEEL
hub_dataflow-0.9.4.dist-info/entry_points.txt
hub_dataflow-0.9.4.dist-info/top_level.txt
hub_dataflow-0.9.4.dist-info/RECORD
